README.md
setup.py
damepandas.egg-info/PKG-INFO
damepandas.egg-info/SOURCES.txt
damepandas.egg-info/dependency_links.txt
damepandas.egg-info/not-zip-safe
damepandas.egg-info/requires.txt
damepandas.egg-info/top_level.txt
damepandas/tests/test_create.py
damepandas/tests/test_json.py
damepandas/tests/test_operators.py
damepandas/tests/test_utils.py