Metadata-Version: 2.1
Name: damepandas
Version: 0.0.10
Summary: Learning Pandas from Tests by David Arroyo Menéndez
Home-page: http://github.com/davidam/damepandas
Author: David Arroyo Menéndez
Author-email: davidam@gnu.org
License: GPLv3
Keywords: pandas numpy tests
Platform: UNKNOWN
Classifier: Development Status :: 3 - Alpha
Classifier: License :: OSI Approved :: GNU General Public License v3 (GPLv3)
Classifier: Programming Language :: Python :: 3.6
Classifier: Topic :: Scientific/Engineering
